np_shared_array/__init__.py
np_shared_array/shared_array.py
np_shared_array-1.0.0.dist-info/LICENSE
np_shared_array-1.0.0.dist-info/METADATA
np_shared_array-1.0.0.dist-info/WHEEL
np_shared_array-1.0.0.dist-info/top_level.txt
np_shared_array-1.0.0.dist-info/RECORD
