Metadata-Version: 2.1
Name: np_shared_array
Version: 1.0.0
Summary: Wrapper for sharing numpy arrays between processes
Author: Tom McLean
Classifier: License :: OSI Approved :: MIT License
Classifier: Programming Language :: Python
Classifier: Programming Language :: Python :: 3
Requires-Python: >=3.9
License-File: LICENSE
Requires-Dist: numpy
